[{"definition":"(an) amount or level of something","difficulty":"B2","partOfSpeech":"noun","word":"degree"},{"definition":"a collection or mass, especially of something that cannot be counted","difficulty":"B1","partOfSpeech":"noun","word":"amount"},{"definition":"a group of objects of one type that have been collected by one person or in one place","difficulty":"B1","partOfSpeech":"noun","word":"collection"},{"definition":"a number of people or things that are put together or considered as a unit","difficulty":"A1","partOfSpeech":"noun","word":"group"},{"definition":"(a sign or symbol representing) a unit that forms part of the system of counting and calculating","difficulty":"A1","partOfSpeech":"noun","word":"number"},{"definition":"to write your name, usually on a written or printed document, to show that you agree with its contents or have written or created it yourself","difficulty":"B1","partOfSpeech":"verb","word":"sign"},{"definition":"belonging or relating to the person or group of people being spoken or written to","difficulty":"A1","partOfSpeech":"determiner","word":"your"}]